LICENSE
MANIFEST.in
README.md
requirements.txt
setup.py
venera/__init__.py
venera/cache.py
venera/channel.py
venera/client.py
venera/flags.py
venera/gateway.py
venera/guild.py
venera/http.py
venera/logs.py
venera/member.py
venera/message.py
venera/readstate.py
venera/role.py
venera/settings.py
venera/user.py
venera.py.egg-info/PKG-INFO
venera.py.egg-info/SOURCES.txt
venera.py.egg-info/dependency_links.txt
venera.py.egg-info/requires.txt
venera.py.egg-info/top_level.txt