Metadata-Version: 2.1
Name: venera.py
Version: 0.1.1
Summary: Asynchronous Venera API Wrapper
Home-page: https://github.com/veneralab/venera.py
Author: Venera
License: MIT
Platform: UNKNOWN
Requires-Python: >=3.9
License-File: LICENSE
